quicken/__init__.py
quicken/__version__.py
quicken/_asyncio.py
quicken/_cli.py
quicken/_client.py
quicken/_constants.py
quicken/_debug.py
quicken/_multiprocessing.py
quicken/_protocol.py
quicken/_server.py
quicken/_signal.py
quicken/_typing.py
quicken/_xdg.py
quicken-0.1.0.dist-info/LICENSE
quicken-0.1.0.dist-info/WHEEL
quicken-0.1.0.dist-info/METADATA
quicken-0.1.0.dist-info/RECORD
